connectkit_s3-3.0.1.dist-info/METADATA
connectkit_s3-3.0.1.dist-info/WHEEL
connectkit_s3-3.0.1.dist-info/entry_points.txt
connectkit_s3-3.0.1.dist-info/licenses/LICENSE
s3/__init__.py
s3/asyncio/__init__.py
s3/asyncio/s3_connector.py
s3/s3_connector.py
s3/settings.py
connectkit_s3-3.0.1.dist-info/RECORD
