Metadata-Version: 2.1
Name: ConnectKit-S3
Version: 3.0.1
Summary: Wrapper for connection to S3
Keywords: connectkit,s3,boto3,async,asyncio,aioboto3,aiofiles
Author-Email: RealMetamorph <andr.timchuk@yandex.ru>
License: The MIT License (MIT)
Classifier: Development Status :: 5 - Production/Stable
Classifier: Programming Language :: Python :: 3
Classifier: Intended Audience :: Developers
Classifier: License :: OSI Approved :: MIT License
Project-URL: Homepage, https://github.com/mtuciru/ConnectKit-S3/blob/3.0.1/README.md
Project-URL: Repository, https://github.com/mtuciru/ConnectKit-S3.git
Requires-Python: >=3.10
Requires-Dist: pydantic>=2.10.6
Requires-Dist: pydantic-settings>=2.8.1
Requires-Dist: boto3>=1.37.1
Provides-Extra: async
Requires-Dist: aiofiles>=24.1.0; extra == "async"
Requires-Dist: aioboto3>=14.1.0; extra == "async"
Requires-Dist: async-lru>=2.0.5; extra == "async"
